netcook_notebook/__init__.py
netcook_notebook/netcook.py
netcook_notebook-0.18.dist-info/METADATA
netcook_notebook-0.18.dist-info/WHEEL
netcook_notebook-0.18.dist-info/entry_points.txt
netcook_notebook-0.18.dist-info/top_level.txt
netcook_notebook-0.18.dist-info/RECORD
