Metadata-Version: 2.1
Name: netcook-notebook
Version: 0.18
Summary: A package to check Netflix cookies status.
Author: NetCook
Author-email: hupbyu36@gmail.com
Classifier: Programming Language :: Python :: 3
Classifier: License :: OSI Approved :: MIT License
Classifier: Operating System :: OS Independent
Requires-Python: >=3.10
Requires-Dist: PyDrive2 ==1.6.3
Requires-Dist: beautifulsoup4 ==4.12.3
Requires-Dist: googletrans ==4.0.0-rc1
Requires-Dist: pandas ==2.0.3
Requires-Dist: pyunpack ==0.3
Requires-Dist: rarfile ==4.2
Requires-Dist: requests ==2.31.0
Requires-Dist: tabulate ==0.9.0
